galsbi/__init__.py
galsbi/citations.py
galsbi/galsbi.py
galsbi/load.py
galsbi/models.py
galsbi/configs/__init__.py
galsbi/configs/config_Fischbacher+24_emulator.py
galsbi/configs/config_Fischbacher+24_image+SE.py
galsbi/configs/config_Fischbacher+24_image.py
galsbi/configs/config_Fischbacher+24_intrinsic.py
galsbi/configs/config_Moser+24_emulator.py
galsbi/configs/config_Moser+24_image+SE.py
galsbi/configs/config_Moser+24_image.py
galsbi/configs/config_Moser+24_intrinsic.py
galsbi/ucat/__init__.py
galsbi/ucat/filters_util.py
galsbi/ucat/galaxy_sampling_util.py
galsbi/ucat/lensing_util.py
galsbi/ucat/magnitude_calculator.py
galsbi/ucat/sed_templates_util.py
galsbi/ucat/spectrum_util.py
galsbi/ucat/utils.py
galsbi/ucat/apps/run_template_filter_integrals.py
galsbi/ucat/config/__init__.py
galsbi/ucat/config/common.py
galsbi/ucat/config/galaxy_catalog.py
galsbi/ucat/galaxy_population_models/__init__.py
galsbi/ucat/galaxy_population_models/galaxy_light_profile.py
galsbi/ucat/galaxy_population_models/galaxy_luminosity_function.py
galsbi/ucat/galaxy_population_models/galaxy_position.py
galsbi/ucat/galaxy_population_models/galaxy_sed.py
galsbi/ucat/galaxy_population_models/galaxy_shape.py
galsbi/ucat/galaxy_population_models/galaxy_size.py
galsbi/ucat/plugins/__init__.py
galsbi/ucat/plugins/apply_shear.py
galsbi/ucat/plugins/galaxy_mag_noise.py
galsbi/ucat/plugins/galaxy_z_noise.py
galsbi/ucat/plugins/sample_galaxies.py
galsbi/ucat/plugins/sample_galaxies_morph.py
galsbi/ucat/plugins/sample_galaxies_photo.py
galsbi/ucat/plugins/write_catalog.py
galsbi/ucat/plugins/write_catalog_photo.py
galsbi-0.2.0.dist-info/METADATA
galsbi-0.2.0.dist-info/WHEEL
galsbi-0.2.0.dist-info/licenses/AUTHORS.rst
galsbi-0.2.0.dist-info/licenses/LICENSE
galsbi-0.2.0.dist-info/RECORD
