Metadata-Version: 2.4
Name: galsbi
Version: 0.2.0
Summary: Package to easily generate catalogs from the model
Project-URL: Repository, https://cosmo-docs.phys.ethz.ch/galsbi
Author-email: Silvan Fischbacher <silvanf@phys.ethz.ch>
License: MIT License
License-File: AUTHORS.rst
License-File: LICENSE
Classifier: Intended Audience :: Developers
Classifier: Intended Audience :: Science/Research
Classifier: License :: OSI Approved :: MIT License
Classifier: Natural Language :: English
Classifier: Operating System :: OS Independent
Classifier: Programming Language :: Python :: 3
Classifier: Programming Language :: Python :: 3.10
Classifier: Programming Language :: Python :: 3.11
Classifier: Programming Language :: Python :: 3.12
Classifier: Programming Language :: Python :: 3.13
Requires-Dist: astropy
Requires-Dist: cosmic-toolbox>=0.4.1
Requires-Dist: cosmo-torrent
Requires-Dist: edelweiss>=0.2.0
Requires-Dist: h5py
Requires-Dist: healpy
Requires-Dist: ivy-wfengine>=0.4.0
Requires-Dist: numpy
Requires-Dist: psutil>=6.1.0
Requires-Dist: pycosmo>=2.2.0
Requires-Dist: scipy
Requires-Dist: ufig>=1.0.0a2
